wo/__init__.py
wo/cloud/__init__.py
wo/cloud/aws.py
wo/cloud/gcp.py
wo/frameworks/__init__.py
wo/frameworks/mlflow.py
wo/orchestrator/__init__.py
wo/orchestrator/kubeflow.py
wo/orchestrator/kubernetes.py
wo/orchestrator/orchestrator.py
wo/orchestrator/storage.py
wo/utils/__init__.py
wo/utils/config.py
wo/utils/io.py
wo-0.1.5.dist-info/METADATA
wo-0.1.5.dist-info/RECORD
wo-0.1.5.dist-info/WHEEL
wo-0.1.5.dist-info/top_level.txt
