Metadata-Version: 2.1
Name: wo
Version: 0.1.5
Summary: Workflow Orchestration tool
Home-page: UNKNOWN
Author: tidylobster
License: Apache 2.0
Platform: UNKNOWN
Requires-Dist: mlflow (~=1.0)
Requires-Dist: boto3 (~=1.9.197)
Requires-Dist: google-cloud-storage (~=1.16.1)
